easy_switchbot/__init__.py
easy_switchbot/api.py
easy_switchbot/devices.py
easy_switchbot/infrared_devices.py
easy_switchbot/statuses.py
easy_switchbot/types.py
easy_switchbot-0.0.4.dist-info/LICENSE
easy_switchbot-0.0.4.dist-info/METADATA
easy_switchbot-0.0.4.dist-info/WHEEL
easy_switchbot-0.0.4.dist-info/top_level.txt
easy_switchbot-0.0.4.dist-info/RECORD
