Metadata-Version: 2.1
Name: easy-switchbot
Version: 0.0.4
Summary: This library provides easy-use to switchbot API.
Author-email: mutoxu=N <dev.mutoh@gmail.com>
Project-URL: Homepage, https://github.com/mutoxu-N/SwitchbotAPI
License-File: LICENSE
